odoo/addons/purchase_invoice_method/README.rst
odoo/addons/purchase_invoice_method/__init__.py
odoo/addons/purchase_invoice_method/__manifest__.py
odoo/addons/purchase_invoice_method/i18n/es.po
odoo/addons/purchase_invoice_method/i18n/it.po
odoo/addons/purchase_invoice_method/i18n/purchase_invoice_method.pot
odoo/addons/purchase_invoice_method/models/__init__.py
odoo/addons/purchase_invoice_method/models/purchase_order.py
odoo/addons/purchase_invoice_method/readme/CONTRIBUTORS.rst
odoo/addons/purchase_invoice_method/readme/DESCRIPTION.rst
odoo/addons/purchase_invoice_method/readme/USAGE.rst
odoo/addons/purchase_invoice_method/static/description/icon.png
odoo/addons/purchase_invoice_method/static/description/index.html
odoo/addons/purchase_invoice_method/tests/__init__.py
odoo/addons/purchase_invoice_method/tests/test_purchase_invoice_method.py
odoo/addons/purchase_invoice_method/views/purchase_order.xml
odoo14_addon_purchase_invoice_method-14.0.1.0.1.dev8.dist-info/METADATA
odoo14_addon_purchase_invoice_method-14.0.1.0.1.dev8.dist-info/WHEEL
odoo14_addon_purchase_invoice_method-14.0.1.0.1.dev8.dist-info/top_level.txt
odoo14_addon_purchase_invoice_method-14.0.1.0.1.dev8.dist-info/RECORD
