Metadata-Version: 2.1
Name: odoo14-addon-purchase_invoice_method
Version: 14.0.1.0.1.dev8
Summary: Allow to force the invoice method of a purchase
Home-page: https://github.com/OCA/purchase-workflow
Author: CreuBlanca,Odoo Community Association (OCA)
Author-email: support@odoo-community.org
License: AGPL-3
Classifier: Programming Language :: Python
Classifier: Framework :: Odoo
Classifier: Framework :: Odoo :: 14.0
Classifier: License :: OSI Approved :: GNU Affero General Public License v3
Requires-Python: >=3.6
Requires-Dist: odoo<14.1dev,>=14.0a
